updateGempa/__init__.py
earthquakereport_indonesia-0.1.5.dist-info/LICENSE
earthquakereport_indonesia-0.1.5.dist-info/METADATA
earthquakereport_indonesia-0.1.5.dist-info/WHEEL
earthquakereport_indonesia-0.1.5.dist-info/top_level.txt
earthquakereport_indonesia-0.1.5.dist-info/RECORD
