Metadata-Version: 2.1
Name: earthquakereport-indonesia
Version: 0.1.5
Summary: This package will provide the most update of Indonesian bureau of Forecast (BMKG)
Home-page: https://github.com/ganirh0612/indonesiaEarthquakeReport
Author: Hasan Gani
Author-email: ganirh0612@gmail.com
Project-URL: Bug Tracker, https://github.com/pypa/sampleproject/issues
Classifier: Programming Language :: Python :: 3
Classifier: Development Status :: 2 - Pre-Alpha
Classifier: License :: OSI Approved :: GNU General Public License v3 (GPLv3)
Classifier: Operating System :: OS Independent
License-File: LICENSE
